ezlocaldb/__init__.py
ezlocaldb-0.0.1.dist-info/LICENSE
ezlocaldb-0.0.1.dist-info/METADATA
ezlocaldb-0.0.1.dist-info/WHEEL
ezlocaldb-0.0.1.dist-info/top_level.txt
ezlocaldb-0.0.1.dist-info/RECORD
