Metadata-Version: 2.1
Name: ezlocaldb
Version: 0.0.1
Summary: Easy local SQL databases for no-sweat persistence
Author-email: Sterling Collins <sterlingcollins@gmail.com>
License: MIT License
Keywords: Database,SQL,Persistence
Classifier: Programming Language :: Python :: 3
Classifier: License :: OSI Approved :: MIT License
Classifier: Operating System :: OS Independent
Requires-Python: >=3.8
License-File: LICENSE
Requires-Dist: appdirs
Requires-Dist: sqlalchemy
Provides-Extra: dev
Requires-Dist: black ; extra == 'dev'
Requires-Dist: pytest ; extra == 'dev'
Requires-Dist: pre-commit ; extra == 'dev'
Requires-Dist: bumpver ; extra == 'dev'
Requires-Dist: tox ; extra == 'dev'
Requires-Dist: mypy ; extra == 'dev'
